k8s_audit_filter/__about__.py
k8s_audit_filter/__init__.py
k8s_audit_filter/abstract_classes.py
k8s_audit_filter/audit_data.py
k8s_audit_filter/audit_filter.py
k8s_audit_filter/count_rules.py
k8s_audit_filter/fields.py
k8s_audit_filter/resourses_field.py
k8s_audit_filter/rules.py
k8s_audit_filter/utils.py
k8s_audit_filter-0.5.0.dist-info/METADATA
k8s_audit_filter-0.5.0.dist-info/WHEEL
k8s_audit_filter-0.5.0.dist-info/licenses/LICENSE
k8s_audit_filter-0.5.0.dist-info/RECORD
