Metadata-Version: 2.1
Name: k8s-audit-filter
Version: 0.5.0
Summary: A tool to filter k8s audit logs
Project-URL: Homepage, https://github.com/petrishutin/k8s-audit-filter
Project-URL: Tracker, https://github.com/petrishutin/k8s-audit-filter/issues
Author-email: Petr Ishutinr <ishutinpetrdev@gmail.com>
License-File: LICENSE
Keywords: audit,filter,k8s
Classifier: License :: OSI Approved :: GNU General Public License (GPL)
Classifier: Operating System :: OS Independent
Classifier: Programming Language :: Python :: 3
Requires-Python: >=3.8
Requires-Dist: pyyaml
